quart_rpc/__init__.py
quart_rpc/exceptions.py
quart_rpc/latest.py
quart_rpc/validation.py
quart_rpc/version_1_0/__init__.py
quart_rpc/version_1_0/_protocols.py
quart_rpc/version_1_0/auth_session_key.py
quart_rpc/version_1_0/model.py
quart_rpc/version_1_0/request.py
quart_rpc/version_1_0/response.py
quart_rpc/version_1_0/rpc.py
quart_rpc/version_1_0/utilities.py
quart_rpc/version_1_1/__init__.py
quart_rpc/version_1_1/_protocols.py
quart_rpc/version_1_1/auth_session_key.py
quart_rpc/version_1_1/model.py
quart_rpc/version_1_1/request.py
quart_rpc/version_1_1/response.py
quart_rpc/version_1_1/rpc.py
quart_rpc/version_1_1/utilities.py
quart_rpc-1.6.3.dist-info/LICENSE
quart_rpc-1.6.3.dist-info/WHEEL
quart_rpc-1.6.3.dist-info/METADATA
quart_rpc-1.6.3.dist-info/RECORD
