Metadata-Version: 2.1
Name: quart-rpc
Version: 1.6.3
Summary: Turn Quart into a simple RPC server
Author-email: David Carmichael <david@uilix.com>
Classifier: Programming Language :: Python :: 3.8
Classifier: Programming Language :: Python :: 3.9
Classifier: Programming Language :: Python :: 3.10
Classifier: Programming Language :: Python :: 3.11
Classifier: Programming Language :: Python :: 3.12
Classifier: License :: OSI Approved :: MIT License
Classifier: Topic :: Internet :: WWW/HTTP :: Dynamic Content
Classifier: Natural Language :: English
Requires-Dist: Quart
Requires-Dist: pydantic
